fastapi_ratelimiter/__init__.py
fastapi_ratelimiter/depends.py
fastapi_ratelimiter/middlewares.py
fastapi_ratelimiter/strategies.py
fastapi_ratelimiter/types.py
fastapi_ratelimiter/utils.py
fastapi_ratelimiter-0.0.2.dist-info/LICENSE
fastapi_ratelimiter-0.0.2.dist-info/WHEEL
fastapi_ratelimiter-0.0.2.dist-info/METADATA
fastapi_ratelimiter-0.0.2.dist-info/RECORD
