Metadata-Version: 2.1
Name: fastapi-ratelimiter
Version: 0.0.2
Summary: Redis-based rate-limiting for FastAPI
Home-page: https://github.com/GLEF1X/fastapi-ratelimit
Keywords: python,fastapi,asgi,asyncio,aiohttp,ratelimit,redis
Author: GLEF1X
Maintainer: GLEF1X
Maintainer-email: glebgar567@gmail.com
Requires-Python: >=3.7,<4.0
Classifier: Programming Language :: Python :: 3
Classifier: Programming Language :: Python :: 3.10
Classifier: Programming Language :: Python :: 3.7
Classifier: Programming Language :: Python :: 3.8
Classifier: Programming Language :: Python :: 3.9
Requires-Dist: aioredis (>=2.0.1,<3.0.0)
Requires-Dist: fastapi (>=0.73.0,<0.74.0)
Project-URL: Repository, https://github.com/GLEF1X/fastapi-ratelimit
